goesgcp/__init__.py
goesgcp/main.py
goesgcp-3.0.2.dist-info/licenses/LICENSE
goesgcp-3.0.2.dist-info/METADATA
goesgcp-3.0.2.dist-info/WHEEL
goesgcp-3.0.2.dist-info/entry_points.txt
goesgcp-3.0.2.dist-info/top_level.txt
goesgcp-3.0.2.dist-info/RECORD
