Metadata-Version: 2.4
Name: goesgcp
Version: 3.0.2
Summary: A package to download and process GOES-16/17 data
Home-page: https://github.com/helvecioneto/goesgcp
Author: Helvecio B. L. Neto
Author-email: helvecioblneto@gmail.com
License: LICENSE
Classifier: Programming Language :: Python
Classifier: Development Status :: 5 - Production/Stable
Classifier: Operating System :: OS Independent
Classifier: Programming Language :: Python :: 3.10
Classifier: Programming Language :: Python :: 3.11
Classifier: Programming Language :: Python :: 3.12
Classifier: Topic :: Scientific/Engineering :: Atmospheric Science
Classifier: Topic :: Scientific/Engineering :: GIS
Classifier: Topic :: Scientific/Engineering
Classifier: Topic :: Software Development
Classifier: Topic :: Utilities
License-File: LICENSE
Requires-Dist: pandas
Requires-Dist: xarray
Requires-Dist: rioxarray
Requires-Dist: google-cloud-storage
Requires-Dist: netcdf4
Requires-Dist: tqdm
Requires-Dist: setuptools
Dynamic: author
Dynamic: author-email
Dynamic: classifier
Dynamic: description
Dynamic: description-content-type
Dynamic: home-page
Dynamic: license
Dynamic: license-file
Dynamic: requires-dist
Dynamic: summary
